screenly_ose/__init__.py
screenly_ose/const.py
screenly_ose/main.py
screenly_ose-0.0.4.dist-info/LICENSE
screenly_ose-0.0.4.dist-info/METADATA
screenly_ose-0.0.4.dist-info/WHEEL
screenly_ose-0.0.4.dist-info/top_level.txt
screenly_ose-0.0.4.dist-info/RECORD
