Metadata-Version: 2.1
Name: screenly-ose
Version: 0.0.4
Summary: Library to enable control of Screenly OSE digital signage via REST API.
Home-page: https://github.com/burnnat/screenly_ose
Author: Nat Burns
Author-email: nbaccount@burnskids.com
License: MIT license
Keywords: screenly_ose
Platform: UNKNOWN
Classifier: Development Status :: 2 - Pre-Alpha
Classifier: Intended Audience :: Developers
Classifier: License :: OSI Approved :: MIT License
Classifier: Natural Language :: English
Classifier: Programming Language :: Python :: 3.5
Classifier: Programming Language :: Python :: 3.6
Classifier: Programming Language :: Python :: 3.7
Classifier: Programming Language :: Python :: 3.8
Classifier: Operating System :: OS Independent
Classifier: Topic :: Software Development :: Libraries :: Python Modules
Requires-Dist: aiohttp
